{
  "updated_at": 1768765744671,
  "data": [
    {
      "region": "日本",
      "status": "正常",
      "username": "justinamenendez569@gmail.com",
      "password": "By55114&"
    },
    {
      "region": "台湾",
      "status": "正常",
      "username": "ke0vi7n9fo0r@icloud.com",
      "password": "Qj66881."
    },
    {
      "region": "美国",
      "status": "正常",
      "username": "elski20d5b5fx773831@icloud.com",
      "password": "Ut44229."
    },
    {
      "region": "香港",
      "status": "正常",
      "username": "la4nc6e7ch7a@icloud.com",
      "password": "Cb99338@"
    },
    {
      "region": "韩国",
      "status": "正常",
      "username": "harryvr2brownszo@gmail.com",
      "password": "Aq66772&"
    },
    {
      "region": "香港",
      "status": "正常",
      "username": "LilyG355sfnddd@icloud.com",
      "password": "Cn55663$"
    },
    {
      "region": "台湾",
      "status": "正常",
      "username": "ro4ge4r8pa3r@icloud.com",
      "password": "Ys55669$"
    },
    {
      "region": "日本",
      "status": "正常",
      "username": "ceijunkaka@icloud.com",
      "password": "Ds11006@"
    },
    {
      "region": "中国",
      "status": "正常",
      "username": "ceirongkaka@icloud.com",
      "password": "Dq66991@"
    },
    {
      "region": "中国",
      "status": "正常",
      "username": "ja4re3d4ba4r@icloud.com",
      "password": "Ug99448@"
    }
  ]
}