{
  "updated_at": 1768535421037,
  "data": [
    {
      "region": "韩国",
      "status": "正常",
      "username": "harper.matth604@icloud.com",
      "password": "Ru44227&"
    },
    {
      "region": "韩国",
      "status": "正常",
      "username": "harryvr2brownszo@gmail.com",
      "password": "Du55449$"
    },
    {
      "region": "香港",
      "status": "正常",
      "username": "la4nc6e7ch7a@icloud.com",
      "password": "Ia77335."
    },
    {
      "region": "中国",
      "status": "正常",
      "username": "ceirongkaka@icloud.com",
      "password": "Zp99550@"
    },
    {
      "region": "台湾",
      "status": "正常",
      "username": "ke0vi7n9fo0r@icloud.com",
      "password": "Bu33008@"
    },
    {
      "region": "美国",
      "status": "正常",
      "username": "abigail.natalie522@icloud.com",
      "password": "Ue88335."
    },
    {
      "region": "美国",
      "status": "正常",
      "username": "Hedvigkwc94@musiccamp.co",
      "password": "Ez33559@"
    },
    {
      "region": "美国",
      "status": "正常",
      "username": "kilianqaccl@gmail.com",
      "password": "Az22998."
    }
  ]
}